{
	"title":[
		{
			"title":"服务报价",
			"pri":"PRICE",
			"del":"Welcome To MIYA photography"
			}
	],
	"txtA":[
		{
			"img":"images/d.png",
			"img1":"images/m1.jpg",
			"titl":"三亚五天套餐价格18999",
			"txt1":"拍摄时间：2014年5月20日~6月5日 美丽四川、美丽九寨 2014年九寨沟婚纱摄影、花湖婚纱摄影团拍档期开始预定啦！",
			"txt":"三亚拍五天婚纱照套餐价格18999元 【拍摄地点】三亚、大东海、三亚湾、亚龙湾、蜈支洲岛 【摄影模式】资深摄影师、化妆师一对一全程贴心服务；免费提供新人两人总计20万元旅游意外保险； 【关于服装】所有婚纱礼服不分区域任选； 【拍摄提供】 女士婚纱礼服8套...",
			"more":"了解更多"
		},
		{
			"img":"images/d.png",
			"img1":"images/m1.jpg",
			"titl":"1天丽江双廊婚纱价格3999",
			"txt1":"拍摄时间：2014年5月20日~6月5日 美丽四川、美丽九寨 2014年九寨沟婚纱摄影、花湖婚纱摄影团拍档期开始预定啦！",
			"txt":"丽江双廊拍一天婚纱照套餐价格3999元 【可选地点】丽江或双廊一天 【摄影模式】资深摄影师、化妆师一对一全程贴心服务；免费提供新人两人总计20万元旅游意外保险； 【关于服装】所有婚纱礼服不分区域任选 【拍摄提供】 女士婚纱礼服3套 女士化妆造型3组 男士...",
			"more":"了解更多"
		},
		{
			"img":"images/d.png",
			"img1":"images/m1.jpg",
			"titl":"九寨沟一天A套餐价格3999",
			"txt1":"拍摄时间：2014年5月20日~6月5日 美丽四川、美丽九寨 2014年九寨沟婚纱摄影、花湖婚纱摄影团拍档期开始预定啦！",
			"txt":"九寨沟拍一天婚纱照A套餐价格3999元 【可选地点】九寨沟 【摄影模式】资深摄影师、化妆师一对一全程贴心服务；免费提供新人两人总计20万元旅游意外保险； 【关于服装】所有婚纱礼服不分区域任选 【拍摄提供】 女士婚纱礼服3套 女士化妆造型3组 男士豪华礼服3...",
			"more":"了解更多"
			}
	]
}